hhrl/.gitignore
hhrl/.ipynb_checkpoints/240409_prj_analysis-checkpoint.ipynb
hhrl/.ipynb_checkpoints/240410_python_conda_parallel-checkpoint.ipynb
hhrl/.ipynb_checkpoints/240415_Revised_jnius_env-checkpoint.py
hhrl/.ipynb_checkpoints/241104.singlecell-hyflex-checkpoint.ipynb
hhrl/.ipynb_checkpoints/241104_gym(0.26.1)_display_server-checkpoint.ipynb
hhrl/.ipynb_checkpoints/241104_gym_pyhyflex-checkpoint.ipynb
hhrl/.ipynb_checkpoints/241104_sb3_test-checkpoint.ipynb
hhrl/.ipynb_checkpoints/Untitled-checkpoint.ipynb
hhrl/.ipynb_checkpoints/__init__-checkpoint.py
hhrl/.ipynb_checkpoints/compare_with_chesc-checkpoint.py
hhrl/.ipynb_checkpoints/fix_experiment_dirs-checkpoint.py
hhrl/.ipynb_checkpoints/generate_graphs-checkpoint.py
hhrl/.ipynb_checkpoints/graphs-checkpoint.py
hhrl/.ipynb_checkpoints/gym_env_wrapper-checkpoint.py
hhrl/.ipynb_checkpoints/hh_project_summary-checkpoint.txt
hhrl/.ipynb_checkpoints/hh_project_summary_onlyfile-checkpoint.txt
hhrl/.ipynb_checkpoints/requirements-checkpoint.txt
hhrl/.ipynb_checkpoints/run-checkpoint.sh
hhrl/.ipynb_checkpoints/runner-checkpoint.py
hhrl/.ipynb_checkpoints/stattests-checkpoint.py
hhrl/.ipynb_checkpoints/temp-checkpoint.txt
hhrl/.ipynb_checkpoints/untitled-checkpoint.py
hhrl/240409_prj_analysis.ipynb
hhrl/240410_python_conda_parallel.ipynb
hhrl/240415_Revised_jnius_env.py
hhrl/241104.singlecell-hyflex.ipynb
hhrl/241104_gym(0.26.1)_display_server.ipynb
hhrl/241104_gym_pyhyflex.ipynb
hhrl/241104_sb3_test.ipynb
hhrl/HH-RL.zip
hhrl/LunarLander_result.gif
hhrl/MountainCar_result.gif
hhrl/README.md
hhrl/Untitled.ipynb
hhrl/__init__.py
hhrl/compare_with_chesc.py
hhrl/configs/.ipynb_checkpoints/default-config-checkpoint.ini
hhrl/configs/.ipynb_checkpoints/epsilon_10-checkpoint.ini
hhrl/configs/.ipynb_checkpoints/fir_discrete-checkpoint.ini
hhrl/configs/.ipynb_checkpoints/rank_decay_05-checkpoint.ini
hhrl/configs/default-config.ini
hhrl/configs/epsilon_10.ini
hhrl/configs/fir_discrete.ini
hhrl/configs/lr_001.ini
pyhyflex-0.1.13.dist-info/METADATA
pyhyflex-0.1.13.dist-info/WHEEL
pyhyflex-0.1.13.dist-info/RECORD
