Metadata-Version: 2.4
Name: pyhyflex
Version: 0.1.13
Summary: 
Author: labATscifn.co
Author-email: you@example.com
Requires-Python: >=3.10
Classifier: Programming Language :: Python :: 3
Classifier: Programming Language :: Python :: 3.10
Classifier: Programming Language :: Python :: 3.11
Classifier: Programming Language :: Python :: 3.12
Classifier: Programming Language :: Python :: 3.13
Classifier: Programming Language :: Python :: 3.14
Requires-Dist: gymnasium (==1.2.3)
Requires-Dist: matplotlib (==3.10.8)
Requires-Dist: numpy (==2.2.6)
Requires-Dist: pyjnius (==1.7.0)
Requires-Dist: stable-baselines3 (==2.7.1)
